bin/download-wikimedia-images.py
bin/lib/autoautoscl/__init__.py
bin/lib/autoautoscl/__main__.py
bin/lib/autoscl/__init__.py
bin/lib/autoscl/__main__.py
doc/conf.py
scal/__init__.py
scal/__main__.py
scal/calendar.py
scal/errors.py
scal/utils.py
scal/data/__init__.py
scal/data/config/calendar.tex
scal/data/config/monthly.tex
scal/data/config/weekly.tex
scal/data/templates/calendar.tex
scal/data/templates/monthly.tex
scal/data/templates/weekly.tex
scal/monthly/__init__.py
scal/monthly/__main__.py
scal/template/__init__.py
scal/template/commands.py
scal-2.5.0.dist-info/licenses/AUTHORS
scal-2.5.0.dist-info/licenses/LICENSE
scal-2.5.0.dist-info/METADATA
scal-2.5.0.dist-info/WHEEL
scal-2.5.0.dist-info/entry_points.txt
scal-2.5.0.dist-info/top_level.txt
scal-2.5.0.dist-info/RECORD
