Metadata-Version: 2.4
Name: scal
Version: 2.5.0
Summary: LaTeX generation of calendars
Home-page: http://framagit.org/spalax/scal
Author: Louis Paternault
Author-email: spalax@gresille.org
License: "GPL-3.0-or-later"
Project-URL: Documentation, http://scal.readthedocs.io
Project-URL: Source, https://framagit.org/spalax/scal
Project-URL: Tracker, https://framagit.org/spalax/scal/issues
Keywords: calendar latex tikz
Classifier: Development Status :: 5 - Production/Stable
Classifier: Environment :: Console
Classifier: Intended Audience :: Education
Classifier: Operating System :: OS Independent
Classifier: Programming Language :: Python
Classifier: Programming Language :: Python :: 3
Classifier: Programming Language :: Python :: 3.12
Classifier: Programming Language :: Python :: 3.13
Classifier: Programming Language :: Python :: 3.14
Classifier: Topic :: Software Development :: Code Generators
Classifier: Topic :: Text Processing :: Markup :: LaTeX
Requires-Python: <4,>=3.12
License-File: LICENSE
License-File: AUTHORS
Requires-Dist: argdispatch>=1.5.0
Requires-Dist: jinja2
Requires-Dist: papersize>=1.7.0
Requires-Dist: pillow
Requires-Dist: pyyaml
Dynamic: license-file
